gradle.properties
hexdoc_hextweaks/__gradle_version__.py
hexdoc_hextweaks/__init__.py
hexdoc_hextweaks/__version__.py
hexdoc_hextweaks/_hooks.py
hexdoc_hextweaks/py.typed
hexdoc_hextweaks/_export/.gitignore
hexdoc_hextweaks/_export/__init__.py
hexdoc_hextweaks/_export/generated/__init__.py
hexdoc_hextweaks/_export/generated/hextweaks.hexdoc.json
hexdoc_hextweaks/_export/generated/hextweaks.patterns.hexdoc.json
hexdoc_hextweaks/_export/generated/assets/computercraft/lang/en_us.json
hexdoc_hextweaks/_export/generated/assets/computercraft/lang/zh_cn.json
hexdoc_hextweaks/_export/generated/assets/computercraft/models/block/turtle_advanced.json
hexdoc_hextweaks/_export/generated/assets/computercraft/models/block/turtle_base.json
hexdoc_hextweaks/_export/generated/assets/computercraft/models/item/turtle_advanced.json
hexdoc_hextweaks/_export/generated/assets/computercraft/textures/block/turtle_advanced_back.png
hexdoc_hextweaks/_export/generated/assets/computercraft/textures/block/turtle_advanced_backpack.png
hexdoc_hextweaks/_export/generated/assets/computercraft/textures/block/turtle_advanced_bottom.png
hexdoc_hextweaks/_export/generated/assets/computercraft/textures/block/turtle_advanced_front.png
hexdoc_hextweaks/_export/generated/assets/computercraft/textures/block/turtle_advanced_left.png
hexdoc_hextweaks/_export/generated/assets/computercraft/textures/block/turtle_advanced_right.png
hexdoc_hextweaks/_export/generated/assets/computercraft/textures/block/turtle_advanced_top.png
hexdoc_hextweaks/_export/generated/assets/hexcasting/lang/en_us.flatten.json5
hexdoc_hextweaks/_export/generated/assets/hexcasting/patchouli_books/thehexbook/en_us/categories/patterns/grand.json
hexdoc_hextweaks/_export/generated/assets/hexcasting/patchouli_books/thehexbook/en_us/categories/patterns/grand/mindflay_rituals.json
hexdoc_hextweaks/_export/generated/assets/hexcasting/patchouli_books/thehexbook/en_us/entries/interop/computercraft.json
hexdoc_hextweaks-5.3.3.1.0.dev0.dist-info/METADATA
hexdoc_hextweaks-5.3.3.1.0.dev0.dist-info/WHEEL
hexdoc_hextweaks-5.3.3.1.0.dev0.dist-info/entry_points.txt
hexdoc_hextweaks-5.3.3.1.0.dev0.dist-info/RECORD
