Metadata-Version: 2.4
Name: hexdoc-hextweaks
Version: 5.3.3.1.0.dev0
Summary: Python web book docgen and hexdoc plugin for HexTweaks.
Project-URL: Homepage, https://walksanatora.github.io/HexTweaks/
Project-URL: Source, https://github.com/walksanatora/Hextweaks
Author: walksanatora
Keywords: hexdoc
Requires-Python: >=3.11
Requires-Dist: hexdoc-hexcasting~=0.11.2.1.0.dev20
Requires-Dist: hexdoc>=1!0.1.0a24
Provides-Extra: dev
Requires-Dist: ruff~=0.1.4; extra == 'dev'
